MANIFEST.in
setup.cfg
setup.py
ymir/__init__.py
ymir/api.py
ymir/base.py
ymir/beanstalk.py
ymir/caching.py
ymir/checks.py
ymir/commands.py
ymir/loom.py
ymir/security_groups.py
ymir/version.py
ymir.egg-info/PKG-INFO
ymir.egg-info/SOURCES.txt
ymir.egg-info/dependency_links.txt
ymir.egg-info/entry_points.txt
ymir.egg-info/not-zip-safe
ymir.egg-info/requires.txt
ymir.egg-info/top_level.txt
ymir/bin/__init__.py
ymir/bin/_ymir.py
ymir/data/__init__.py
ymir/mixins/__init__.py
ymir/mixins/_ansible.py
ymir/mixins/_fabric.py
ymir/mixins/packages.py
ymir/mixins/puppet.py
ymir/mixins/rsync.py
ymir/schema/__init__.py
ymir/schema/base.py
ymir/schema/data.py
ymir/schema/security_groups.py
ymir/schema/validators.py
ymir/service/__init__.py
ymir/service/_vagrant.py
ymir/service/amazon.py
ymir/service/base.py
ymir/skeleton/.ymir
ymir/skeleton/README.md
ymir/skeleton/Vagrantfile
ymir/skeleton/__init__.py
ymir/skeleton/__init__.pyc
ymir/skeleton/fabfile.py
ymir/skeleton/fabfile.pyc
ymir/skeleton/hiera.yaml
ymir/skeleton/security_groups.json
ymir/skeleton/service.json
ymir/skeleton/vagrant.json
ymir/skeleton/ansible/README.md
ymir/skeleton/ansible/play.yml
ymir/skeleton/ansible/requirements.yml
ymir/skeleton/ansible/ymir_inventory.py
ymir/skeleton/ansible/library/README.md
ymir/skeleton/ansible/roles/common/README.md
ymir/skeleton/ansible/roles/common/defaults/.placeholder
ymir/skeleton/ansible/roles/common/files/.placeholder
ymir/skeleton/ansible/roles/common/group_vars/.placeholder
ymir/skeleton/ansible/roles/common/handlers/.placeholder
ymir/skeleton/ansible/roles/common/host_vars/.placeholder
ymir/skeleton/ansible/roles/common/meta/.placeholder
ymir/skeleton/ansible/roles/common/tasks/.placeholder
ymir/skeleton/ansible/roles/common/templates/.placeholder
ymir/skeleton/ansible/roles/common/vars/.placeholder
ymir/skeleton/ansible/templates/README.md
ymir/skeleton/puppet/README.md
ymir/skeleton/puppet/demo_service.pp
ymir/skeleton/puppet/metadata.json
ymir/skeleton/puppet/modules/ymir/ec2_facts.pp
ymir/skeleton/puppet/modules/ymir/install_librarian.pp
ymir/skeleton/puppet/modules/ymir/log_dirs.pp
ymir/skeleton/puppet/modules/ymir/packages.pp
